{"name": "LSASS Memory Dump", "description": "Detects process LSASS memory dump using procdump or taskmgr based on the CallTrace pointing to dbghelp.dll or dbgcore.dll for win10", "created": "2019-04-03T00:00:00.000Z", "valid_from": "2019-04-03T00:00:00Z", "indicator_types": ["malicious-activity"], "pattern_type": "sigma", "pattern": "title: LSASS Memory Dump\nid: 5ef9853e-4d0e-4a70-846f-a9ca37d876da\nstatus: experimental\ndescription: Detects process LSASS memory dump using procdump or taskmgr based on the CallTrace pointing to dbghelp.dll or dbgcore.dll for win10\nauthor: Samir Bousseaden\ndate: 2019/04/03\nreferences:\n    - https://blog.menasec.net/2019/02/threat-hunting-21-procdump-or-taskmgr.html\ntags:\n    - attack.t1003\n    - attack.s0002\n    - attack.credential_access\nlogsource:\n    product: windows\n    service: sysmon\ndetection:\n    selection:\n        EventID: 10\n        TargetImage: 'C:\\windows\\system32\\lsass.exe'\n        GrantedAccess: '0x1fffff'\n        CallTrace:\n         - '*dbghelp.dll*'\n         - '*dbgcore.dll*'\n    condition: selection\nfalsepositives:\n    - unknown\nlevel: high\n", "object_marking_refs": ["marking-definition--0a872d70-1d05-45dd-a25f-031af547a102"], "created_by_ref": "identity--082ca4f0-d825-45b6-aa42-ab9afd1e5503", "type": "indicator", "spec_version": "2.1", "id": "indicator--8fdeb433-54e9-4beb-96df-e1b3346dc7cb", "modified": "2020-04-02T10:15:00.986Z"}