{"name": "Empire PowerShell UAC Bypass", "description": "Detects some Empire PowerShell UAC bypass methods", "created": "2019-08-30T00:00:00.000Z", "valid_from": "2019-08-30T00:00:00Z", "indicator_types": ["malicious-activity"], "pattern_type": "sigma", "pattern": "title: Empire PowerShell UAC Bypass\nid: 3268b746-88d8-4cd3-bffc-30077d02c787\nstatus: experimental\ndescription: Detects some Empire PowerShell UAC bypass methods\nreferences:\n    - https://github.com/EmpireProject/Empire/blob/e37fb2eef8ff8f5a0a689f1589f424906fe13055/data/module_source/privesc/Invoke-EventVwrBypass.ps1#L64\n    - https://github.com/EmpireProject/Empire/blob/e37fb2eef8ff8f5a0a689f1589f424906fe13055/data/module_source/privesc/Invoke-FodHelperBypass.ps1#L64\nauthor: Ecco\ndate: 2019/08/30\nlogsource:\n    category: process_creation\n    product: windows\ndetection:\n    selection:\n        CommandLine:\n            - '* -NoP -NonI -w Hidden -c $x=$((gp HKCU:Software\\\\Microsoft\\\\Windows Update).Update)*'\n            - '* -NoP -NonI -c $x=$((gp HKCU:Software\\\\Microsoft\\\\Windows Update).Update);*'\n    condition: selection\nfields:\n    - CommandLine\n    - ParentCommandLine\ntags:\n    - attack.defense_evasion\n    - attack.privilege_escalation\n    - attack.t1088\n    - car.2019-04-001\nfalsepositives:\n    - unknown\nlevel: critical\n", "object_marking_refs": ["marking-definition--0a872d70-1d05-45dd-a25f-031af547a102"], "created_by_ref": "identity--082ca4f0-d825-45b6-aa42-ab9afd1e5503", "type": "indicator", "spec_version": "2.1", "id": "indicator--2d670ca1-44e5-4b4a-a4cc-fe26c5f55aa9", "modified": "2020-04-02T10:14:49.897Z"}