{"name": "System File Execution Location Anomaly", "description": "Detects a Windows program executable started in a suspicious folder", "created": "2017-11-27T00:00:00.000Z", "valid_from": "2017-11-27T00:00:00Z", "indicator_types": ["malicious-activity"], "pattern_type": "sigma", "pattern": "title: System File Execution Location Anomaly\nid: e4a6b256-3e47-40fc-89d2-7a477edd6915\nstatus: experimental\ndescription: Detects a Windows program executable started in a suspicious folder\nreferences:\n    - https://twitter.com/GelosSnake/status/934900723426439170\nauthor: Florian Roth, Patrick Bareiss\ndate: 2017/11/27\ntags:\n    - attack.defense_evasion\n    - attack.t1036\nlogsource:\n    category: process_creation\n    product: windows\ndetection:\n    selection:\n        Image:\n            - '*\\svchost.exe'\n            - '*\\rundll32.exe'\n            - '*\\services.exe'\n            - '*\\powershell.exe'\n            - '*\\regsvr32.exe'\n            - '*\\spoolsv.exe'\n            - '*\\lsass.exe'\n            - '*\\smss.exe'\n            - '*\\csrss.exe'\n            - '*\\conhost.exe'\n            - '*\\wininit.exe'\n            - '*\\lsm.exe'\n            - '*\\winlogon.exe'\n            - '*\\explorer.exe'\n            - '*\\taskhost.exe'\n    filter:\n        Image:\n            - 'C:\\Windows\\System32\\\\*'\n            - 'C:\\Windows\\system32\\\\*'\n            - 'C:\\Windows\\SysWow64\\\\*'\n            - 'C:\\Windows\\SysWOW64\\\\*'\n            - 'C:\\Windows\\explorer.exe'\n            - 'C:\\Windows\\winsxs\\\\*'\n            - 'C:\\Windows\\WinSxS\\\\*'\n            - '\\SystemRoot\\System32\\\\*'\n    condition: selection and not filter\nfields:\n    - ComputerName\n    - User\n    - Image\nfalsepositives:\n    - Exotic software\nlevel: high\n", "object_marking_refs": ["marking-definition--0a872d70-1d05-45dd-a25f-031af547a102"], "created_by_ref": "identity--082ca4f0-d825-45b6-aa42-ab9afd1e5503", "type": "indicator", "spec_version": "2.1", "id": "indicator--3ee643e8-dd42-4471-a5ca-f986e450bb4b", "modified": "2020-04-02T10:14:50.203Z"}