{"name": "Elise Backdoor", "description": "Detects Elise backdoor acitivty as used by APT32", "created": "2018-01-31T00:00:00.000Z", "valid_from": "2018-01-31T00:00:00Z", "indicator_types": ["malicious-activity"], "pattern_type": "sigma", "pattern": "title: Elise Backdoor\nid: e507feb7-5f73-4ef6-a970-91bb6f6d744f\nstatus: experimental\ndescription: Detects Elise backdoor acitivty as used by APT32\nreferences:\n    - https://community.rsa.com/community/products/netwitness/blog/2018/02/13/lotus-blossom-continues-asean-targeting\ntags:\n    - attack.g0030\n    - attack.g0050\n    - attack.s0081\nauthor: Florian Roth\ndate: 2018/01/31\nlogsource:\n    category: process_creation\n    product: windows\ndetection:\n    selection1:\n        Image: 'C:\\Windows\\SysWOW64\\cmd.exe'\n        CommandLine: '*\\Windows\\Caches\\NavShExt.dll *'\n    selection2:\n        CommandLine: '*\\AppData\\Roaming\\MICROS~1\\Windows\\Caches\\NavShExt.dll,Setting'\n    condition: 1 of them\nfalsepositives:\n    - Unknown\nlevel: critical\n", "object_marking_refs": ["marking-definition--0a872d70-1d05-45dd-a25f-031af547a102"], "created_by_ref": "identity--082ca4f0-d825-45b6-aa42-ab9afd1e5503", "type": "indicator", "spec_version": "2.1", "id": "indicator--0922a61e-54b8-4e53-b721-ebfa137aa7a9", "modified": "2020-04-02T10:14:49.454Z"}