{"name": "Executable in ADS", "description": "Detects the creation of an ADS data stream that contains an executable (non-empty imphash)", "created": "2018-06-03T00:00:00.000Z", "valid_from": "2018-06-03T00:00:00Z", "indicator_types": ["malicious-activity"], "pattern_type": "sigma", "pattern": "title: Executable in ADS\nid: b69888d4-380c-45ce-9cf9-d9ce46e67821\nstatus: experimental\ndescription: Detects the creation of an ADS data stream that contains an executable (non-empty imphash)\nreferences:\n    - https://twitter.com/0xrawsec/status/1002478725605273600?s=21\ntags:\n    - attack.defense_evasion\n    - attack.t1027\n    - attack.s0139\nauthor: Florian Roth, @0xrawsec\ndate: 2018/06/03\nlogsource:\n    product: windows\n    service: sysmon\n    definition: 'Requirements: Sysmon config with Imphash logging activated'\ndetection:\n    selection:\n        EventID: 15\n    filter:\n        Imphash: \n            - '00000000000000000000000000000000'\n            - null\n    condition: selection and not filter\nfields:\n    - TargetFilename\n    - Image\nfalsepositives:\n    - unknown\nlevel: critical\n\n", "object_marking_refs": ["marking-definition--0a872d70-1d05-45dd-a25f-031af547a102"], "created_by_ref": "identity--082ca4f0-d825-45b6-aa42-ab9afd1e5503", "type": "indicator", "spec_version": "2.1", "id": "indicator--4ed994c4-e11b-4b64-b535-ae772d7885ba", "modified": "2020-04-02T10:15:01.474Z"}